{
  "generated_at": "2025-08-23 21:33:32",
  "trends": [
    {
      "keyword": "환율",
      "volume": 31479,
      "difficulty": "상",
      "related": "청년, 지원금",
      "channel": "경제"
    },
    {
      "keyword": "손흥민",
      "volume": 31688,
      "difficulty": "상",
      "related": "청년, 지원금",
      "channel": "스포츠"
    },
    {
      "keyword": "디아블로 출시",
      "volume": 18898,
      "difficulty": "상",
      "related": "재난, 기상청",
      "channel": "경제"
    },
    {
      "keyword": "전세사기",
      "volume": 27101,
      "difficulty": "중",
      "related": "넷플릭스, 구독",
      "channel": "이슈"
    },
    {
      "keyword": "청년도약계좌",
      "volume": 15695,
      "difficulty": "하",
      "related": "청년, 지원금",
      "channel": "스포츠"
    },
    {
      "keyword": "청년 취업지원금",
      "volume": 15620,
      "difficulty": "하",
      "related": "청년, 지원금",
      "channel": "이슈"
    },
    {
      "keyword": "테슬라 주가",
      "volume": 30523,
      "difficulty": "중",
      "related": "넷플릭스, 구독",
      "channel": "이슈"
    },
    {
      "keyword": "넷플릭스 해지",
      "volume": 22662,
      "difficulty": "하",
      "related": "넷플릭스, 구독",
      "channel": "이슈"
    },
    {
      "keyword": "카리나",
      "volume": 24608,
      "difficulty": "상",
      "related": "넷플릭스, 구독",
      "channel": "정책"
    },
    {
      "keyword": "청약 일정",
      "volume": 38295,
      "difficulty": "상",
      "related": "재난, 기상청",
      "channel": "정책"
    },
    {
      "keyword": "아이폰16",
      "volume": 23880,
      "difficulty": "중",
      "related": "재난, 기상청",
      "channel": "경제"
    },
    {
      "keyword": "로또 당첨",
      "volume": 42066,
      "difficulty": "하",
      "related": "넷플릭스, 구독",
      "channel": "스포츠"
    }
  ]
}